malt/__init__.py
malt/_version.py
malt/molecule.py
malt/policy.py
malt/trainer.py
malt/utility_functions.py
malt/agents/__init__.py
malt/agents/agent.py
malt/agents/assayer.py
malt/agents/merchant.py
malt/agents/player.py
malt/data/__init__.py
malt/data/collections.py
malt/data/dataset.py
malt/models/__init__.py
malt/models/regressor.py
malt/models/representation.py
malt/models/supervised_model.py
malt/models/zoo/__init__.py
malt/models/zoo/gat.py
malt/utils/__init__.py
malt/utils/docking.py
malt.wangyq.net-0.0.2a0.dist-info/LICENSE
malt.wangyq.net-0.0.2a0.dist-info/METADATA
malt.wangyq.net-0.0.2a0.dist-info/WHEEL
malt.wangyq.net-0.0.2a0.dist-info/top_level.txt
malt.wangyq.net-0.0.2a0.dist-info/RECORD
